tinydownload/__init__.py
tinydownload/tinydownload.py
tinydownload-0.1.0.dist-info/DESCRIPTION.rst
tinydownload-0.1.0.dist-info/METADATA
tinydownload-0.1.0.dist-info/RECORD
tinydownload-0.1.0.dist-info/WHEEL
tinydownload-0.1.0.dist-info/entry_points.txt
tinydownload-0.1.0.dist-info/metadata.json
tinydownload-0.1.0.dist-info/top_level.txt
