Metadata-Version: 2.0
Name: tinydownload
Version: 0.1.0
Summary: Download files from tinyupload.com
Home-page: https://www.github.com/ritiek/tinydownload
Author: Ritiek Malhotra
Author-email: ritiekmalhotra123@gmail.com
License: MIT
Download-URL: https://github.com/ritiek/tinydownload/archive/v0.1.0.tar.gz
Keywords: tinyupload,downloader,command-line,tinydownload,python
Platform: UNKNOWN
Requires-Dist: BeautifulSoup4
Requires-Dist: requests
